mcp_server_opensearch/__init__.py
mcp_server_opensearch/__main__.py
mcp_server_opensearch/sse_server.py
mcp_server_opensearch/stdio_server.py
opensearch/__init__.py
opensearch/client.py
opensearch/helper.py
opensearch_mcp-0.0.1.dist-info/licenses/LICENSE
tools/__init__.py
tools/tools.py
opensearch_mcp-0.0.1.dist-info/METADATA
opensearch_mcp-0.0.1.dist-info/WHEEL
opensearch_mcp-0.0.1.dist-info/entry_points.txt
opensearch_mcp-0.0.1.dist-info/top_level.txt
opensearch_mcp-0.0.1.dist-info/RECORD
